{"data": {"all_parameters": [], "all_puppetclasses": [], "architecture_id": 1, "architecture_name": "x86_64", "build": false, "capabilities": ["build"], "certname": "w6.i8.example-652.com", "comment": null, "compute_profile_id": null, "compute_profile_name": null, "compute_resource_id": null, "compute_resource_name": null, "config_groups": [], "content_facet_attributes": {"applicable_package_count": 0, "content_source": null, "content_source_id": null, "content_source_name": null, "content_view": {"id": 3, "name": "Satellite 6.2 RHEL7"}, "content_view_default?": false, "content_view_id": 3, "content_view_name": "Satellite 6.2 RHEL7", "content_view_version": "386.0", "content_view_version_id": 4165, "errata_counts": {"bugfix": 0, "enhancement": 0, "security": 0, "total": 0}, "id": 156, "katello_agent_installed": false, "kickstart_repository_id": null, "lifecycle_environment": {"id": 10, "name": "QA"}, "lifecycle_environment_id": 10, "lifecycle_environment_library?": false, "lifecycle_environment_name": "QA", "upgradable_package_count": 0, "uuid": "b695d656-f1a5-4a36-b686-acd00ecb9aa3"}, "created_at": "2016-07-17 16:13:37 UTC", "disk": null, "domain_id": null, "domain_name": null, "enabled": true, "environment_id": null, "environment_name": null, "errata_status": 1, "errata_status_label": "Could not calculate errata status, ensure host is registered and katello-agent is installed", "facts": {"_timestamp": "2016-11-05T13:21:24-04:00", "cpu": null, "cpu::core(s)_per_socket": "8", "cpu::cpu(s)": "32", "cpu::cpu_socket(s)": "2", "cpu::thread(s)_per_core": "2", "cpu::topology_source": "kernel /sys cpu sibling lists", "distribution": null, "distribution::id": "Maipo", "distribution::name": "Red Hat Enterprise Linux Server", "distribution::version": "7.2", "distribution::version::modifier": "ga", "dmi": null, "dmi::baseboard": null, "dmi::baseboard::manufacturer": "Dell Inc.", "dmi::baseboard::product_name": "Not Specified", "dmi::baseboard::serial_number": ".9842282..10.", "dmi::baseboard::version": "Not Specified", "dmi::bios": null, "dmi::bios::address": "0xf0000", "dmi::bios::bios_revision": "1.4", "dmi::bios::relase_date": "10/26/2015", "dmi::bios::rom_size": "16384 KB", "dmi::bios::runtime_size": "64 KB", "dmi::bios::vendor": "Dell Inc.", "dmi::bios::version": "1.4.5", "dmi::chassis": null, "dmi::chassis::asset_tag": "Not Specified", "dmi::chassis::boot-up_state": "Safe", "dmi::chassis::lock": "Not Present", "dmi::chassis::manufacturer": "Dell Inc.", "dmi::chassis::power_supply_state": "Safe", "dmi::chassis::security_status": "Unknown", "dmi::chassis::serial_number": "9842282", "dmi::chassis::thermal_state": "Safe", "dmi::chassis::type": "Multi-system", "dmi::chassis::version": "PowerEdge M1000e", "dmi::connector": null, "dmi::connector::external_connector_type": "Access Bus (USB)", "dmi::connector::external_reference_designator": "Front USB port 2", "dmi::connector::internal_connector_type": "None", "dmi::connector::internal_reference_designator": "Not Specified", "dmi::connector::port_type": "USB", "dmi::memory": null, "dmi::memory::array_handle": "0x1000", "dmi::memory::assettag": "Not Specified", "dmi::memory::bank_locator": "Not Specified", "dmi::memory::error_correction_type": "Multi-bit ECC", "dmi::memory::error_information_handle": "Not Provided", "dmi::memory::form_factor": "Unknown", "dmi::memory::location": "System Board Or Motherboard", "dmi::memory::locator": "B9", "dmi::memory::manufacturer": "Not Specified", "dmi::memory::maximum_capacity": "1536 GB", "dmi::memory::part_number": "Not Specified", "dmi::memory::serial_number": "Not Specified", "dmi::memory::size": "16384 MB", "dmi::memory::speed": "(ns)", "dmi::memory::type": "Unknown", "dmi::memory::use": "System Memory", "dmi::processor": null, "dmi::processor::asset_tag": "Not Specified", "dmi::processor::family": "Xeon", "dmi::processor::l1_cache_handle": "0x0703", "dmi::processor::l2_cache_handle": "0x0704", "dmi::processor::l3_cache_handle": "0x0705", "dmi::processor::part_number": "Not Specified", "dmi::processor::serial_number": "Not Specified", "dmi::processor::socket_designation": "CPU2", "dmi::processor::status": "Populated:Enabled", "dmi::processor::type": "Central Processor", "dmi::processor::version": "Intel(R) Xeon(R) CPU E5-2630 v3 @ 2.40GHz", "dmi::processor::voltage": "1.3 V", "dmi::slot": null, "dmi::slot::current_usage": "Available", "dmi::slot::designation": "Mezzanine 1C", "dmi::slot::slotlength": "Other", "dmi::slot::type:slotbuswidth": "x8", "dmi::system": null, "dmi::system::family": "Not Specified", "dmi::system::manufacturer": "Dell Inc.", "dmi::system::product_name": "PowerEdge M630", "dmi::system::serial_number": "981L182", "dmi::system::sku_number": "SKU=NotProvided;ModelName=PowerEdge M630", "dmi::system::status": "No errors detected", "dmi::system::uuid": "4C4C4544-0038-3110-804C-B9C04F313832", "dmi::system::version": "Not Specified", "dmi::system::wake-up_type": "Power Switch", "lscpu": null, "lscpu::architecture": "x86_64", "lscpu::bogomips": "4792.92", "lscpu::byte_order": "Little Endian", "lscpu::core(s)_per_socket": "8", "lscpu::cpu(s)": "32", "lscpu::cpu_family": "6", "lscpu::cpu_mhz": "1773.656", "lscpu::cpu_op-mode(s)": "32-bit, 64-bit", "lscpu::l1d_cache": "32K", "lscpu::l1i_cache": "32K", "lscpu::l2_cache": "256K", "lscpu::l3_cache": "20480K", "lscpu::model": "63", "lscpu::model_name": "Intel(R) Xeon(R) CPU E5-2630 v3 @ 2.40GHz", "lscpu::numa_node(s)": "2", "lscpu::numa_node0_cpu(s)": "0,2,4,6,8,10,12,14,16,18,20,22,24,26,28,30", "lscpu::numa_node1_cpu(s)": "1,3,5,7,9,11,13,15,17,19,21,23,25,27,29,31", "lscpu::on-line_cpu(s)_list": "0-31", "lscpu::socket(s)": "2", "lscpu::stepping": "2", "lscpu::thread(s)_per_core": "2", "lscpu::vendor_id": "GenuineIntel", "lscpu::virtualization": "VT-x", "memory": null, "memory::memtotal": "131619764", "memory::swaptotal": "4194300", "net": null, "net::interface": null, "net::interface::em1": null, "net::interface::em1::mac_address": "1C:40:24:99:5C:C6", "net::interface::em2": null, "net::interface::em2::ipv4_address": "172.31.2.12", "net::interface::em2::ipv4_broadcast": "172.31.255.255", "net::interface::em2::ipv4_netmask": "16", "net::interface::em2::mac_address": "1C:40:24:99:5C:C8", "net::interface::em3": null, "net::interface::em3::mac_address": "1C:40:24:99:63:92", "net::interface::em4": null, "net::interface::em4::mac_address": "1C:40:24:99:63:94", "net::interface::lo": null, "net::interface::lo::ipv4_address": "127.0.0.1", "net::interface::lo::ipv4_broadcast": "Unknown", "net::interface::lo::ipv4_netmask": "8", "net::interface::lo::ipv6_address": null, "net::interface::lo::ipv6_address::host": "::1", "net::interface::lo::ipv6_netmask": null, "net::interface::lo::ipv6_netmask::host": "128", "net::interface::p2p1": null, "net::interface::p2p1::mac_address": "1C:40:24:99:5C:CA", "net::interface::p2p2": null, "net::interface::p2p2::ipv4_address": "10.19.2.88", "net::interface::p2p2::ipv4_broadcast": "10.19.2.255", "net::interface::p2p2::ipv4_netmask": "24", "net::interface::p2p2::ipv6_address": null, "net::interface::p2p2::ipv6_address::global": "2620:52:0:1302:1e40:24ff:fe99:5ccb", "net::interface::p2p2::ipv6_address::link": "fe80::1e40:24ff:fe99:5ccb", "net::interface::p2p2::ipv6_netmask": null, "net::interface::p2p2::ipv6_netmask::global": "64", "net::interface::p2p2::ipv6_netmask::link": "64", "net::interface::p2p2::mac_address": "1C:40:24:99:5C:CB", "net::interface::p2p3": null, "net::interface::p2p3::mac_address": "1C:40:24:99:5C:CC", "net::interface::p2p4": null, "net::interface::p2p4::mac_address": "1C:40:24:99:5C:CD", "network": null, "network::hostname": "w6.i8.example-652.com", "network::ipv4_address": "10.19.2.10", "network::ipv6_address": "fe80::1e40:24ff:fe99:5ccb, 2620:52:0:1302:1e40:24ff:fe99:5ccb", "system": null, "system::certificate_version": "3.2", "uname": null, "uname::machine": "x86_64", "uname::nodename": "w6.i8.example-652.com", "uname::release": "3.10.0-327.el7.x86_64", "uname::sysname": "Linux", "uname::version": "#1 SMP Thu Oct 29 17:29:29 EDT 2015", "virt": null, "virt::host_type": "Not Applicable", "virt::is_guest": "false"}, "global_status": 2, "global_status_label": "Error", "host_collections": [], "hostgroup_id": null, "hostgroup_name": null, "hostgroup_title": null, "id": 167, "image_file": "", "image_id": null, "image_name": null, "installed_at": null, "interfaces": [{"id": 498, "identifier": "em1", "ip": null, "ip6": null, "mac": "1c:40:24:99:5c:c6", "name": null, "primary": false, "provision": false, "type": "interface"}, {"id": 496, "identifier": "em2", "ip": "172.31.2.12", "ip6": null, "mac": "1c:40:24:99:5c:c8", "name": null, "primary": false, "provision": false, "type": "interface"}, {"id": 499, "identifier": "em3", "ip": null, "ip6": null, "mac": "1c:40:24:99:63:92", "name": null, "primary": false, "provision": false, "type": "interface"}, {"id": 493, "identifier": "em4", "ip": null, "ip6": null, "mac": "1c:40:24:99:63:94", "name": null, "primary": false, "provision": false, "type": "interface"}, {"id": 497, "identifier": "p2p1", "ip": null, "ip6": null, "mac": "1c:40:24:99:5c:ca", "name": null, "primary": false, "provision": false, "type": "interface"}, {"id": 492, "identifier": "p2p2", "ip": "10.19.2.88", "ip6": null, "mac": "1c:40:24:99:5c:cb", "name": "w6.i8.example-652.com", "primary": true, "provision": true, "type": "interface"}, {"id": 494, "identifier": "p2p3", "ip": null, "ip6": null, "mac": "1c:40:24:99:5c:cc", "name": null, "primary": false, "provision": false, "type": "interface"}, {"id": 495, "identifier": "p2p4", "ip": null, "ip6": null, "mac": "1c:40:24:99:5c:cd", "name": null, "primary": false, "provision": false, "type": "interface"}], "ip": "10.19.2.88", "ip6": null, "last_compile": "2016-11-05 17:21:24 UTC", "last_report": null, "location_id": 2, "location_name": "Default Location", "mac": "1c:40:24:99:5c:cb", "managed": false, "medium_id": null, "medium_name": null, "model_id": 33, "model_name": "PowerEdge M630", "name": "w6.i8.example-652.com", "openscap_proxy": null, "openscap_proxy_id": null, "openscap_proxy_name": null, "operatingsystem_id": 2, "operatingsystem_name": "RedHat 7.2", "organization_id": 3, "organization_name": "Sat6-CI", "owner_id": 1, "owner_type": "User", "parameters": [], "permissions": {"auto_provision_discovered_hosts": false, "build_hosts": false, "console_hosts": false, "create_hosts": false, "destroy_discovered_hosts": false, "destroy_hosts": false, "edit_discovered_hosts": false, "edit_hosts": false, "ipmi_boot_hosts": false, "power_hosts": false, "provision_discovered_hosts": false, "puppetrun_hosts": false, "submit_discovered_hosts": false, "view_discovered_hosts": true, "view_hosts": true}, "provision_method": "build", "ptable_id": null, "ptable_name": null, "puppet_ca_proxy": null, "puppet_ca_proxy_id": null, "puppet_ca_proxy_name": null, "puppet_proxy": null, "puppet_proxy_id": null, "puppet_proxy_name": null, "puppet_status": 0, "puppetclasses": [], "pxe_loader": "PXELinux BIOS", "realm_id": null, "realm_name": null, "sp_ip": null, "sp_mac": null, "sp_name": null, "sp_subnet_id": null, "subnet6_id": null, "subnet6_name": null, "subnet_id": null, "subnet_name": null, "subscription_facet_attributes": {"activation_keys": [{"id": 3, "name": "Satellite QA RHEL7"}], "autoheal": true, "compliance_reasons": ["Red Hat Enterprise Linux Server: Not supported by a valid subscription.", "Red Hat Software Collections (for RHEL Server): Not supported by a valid subscription."], "id": 1085, "installed_products": [{"arch": "x86_64", "created": "2016-07-17T19:02:21+0000", "endDate": null, "id": "8a88800f55c09b2e0155fa3cde6e11d5", "productId": "201", "productName": "Red Hat Software Collections (for RHEL Server)", "startDate": null, "status": "red", "updated": "2016-07-17T19:02:21+0000", "version": "2"}, {"arch": "x86_64", "created": "2016-07-17T19:02:21+0000", "endDate": null, "id": "8a88800f55c09b2e0155fa3cde6e11d6", "productId": "69", "productName": "Red Hat Enterprise Linux Server", "startDate": null, "status": "red", "updated": "2016-07-17T19:02:21+0000", "version": "7.2"}], "last_checkin": "2016-08-02 19:02:32 UTC", "registered_at": "2016-07-17 16:13:39 UTC", "registered_through": null, "release_version": null, "service_level": null, "user": null, "uuid": "b695d656-f1a5-4a36-b686-acd00ecb9aa3", "virtual_guests": [], "virtual_host": null}, "subscription_global_status": 2, "subscription_status": 2, "subscription_status_label": "Unentitled", "updated_at": "2017-08-09 14:31:18 UTC", "use_image": null, "uuid": null}, "headers": {"apipie-checksum": "7c9fee53e43cd183bab2af8ddbfe1304", "cache-control": "max-age=0, private, must-revalidate", "connection": "Keep-Alive", "content-encoding": "gzip", "content-length": "3511", "content-security-policy": "default-src 'self'; child-src 'self'; connect-src 'self' ws: wss:; img-src 'self' data: *.gravatar.com; script-src 'unsafe-eval' 'unsafe-inline' 'self'; style-src 'unsafe-inline' 'self'", "content-type": "application/json; charset=utf-8", "date": "Thu, 15 Mar 2018 22:19:36 GMT", "etag": "W/\"3574ab883dd60e5e79f2564b5161843b-gzip\"", "foreman_api_version": "2", "foreman_version": "1.15.6.34", "keep-alive": "timeout=5, max=9194", "server": "Apache/2.4.6 (Red Hat Enterprise Linux)", "status": "200 OK", "strict-transport-security": "max-age=631152000; includeSubdomains", "vary": "Accept-Encoding", "x-content-type-options": "nosniff", "x-download-options": "noopen", "x-frame-options": "sameorigin", "x-permitted-cross-domain-policies": "none", "x-powered-by": "Phusion Passenger 4.0.18", "x-request-id": "d0e2b403-ed6f-40b3-a77c-93584ed44b09", "x-runtime": "0.385487", "x-xss-protection": "1; mode=block"}, "page": 1, "status_code": 200, "url": "https://d1.k8.j1.example-637.com/api/v2/hosts/167"}